django_lokalise-0.1.6.dist-info/DESCRIPTION.rst
django_lokalise-0.1.6.dist-info/entry_points.txt
django_lokalise-0.1.6.dist-info/METADATA
django_lokalise-0.1.6.dist-info/metadata.json
django_lokalise-0.1.6.dist-info/RECORD
django_lokalise-0.1.6.dist-info/top_level.txt
django_lokalise-0.1.6.dist-info/WHEEL
lokalise/__init__.py
lokalise/middleware.py
lokalise/urls.py
lokalise/version.py
lokalise/views.py
tests/__init__.py
tests/base.py
